[{"id":0,"name":"Madelina","gender":"male"},{"id":1,"name":"Keriann","gender":"famale"},{"id":2,"name":"Melessa","gender":"famale"},{"id":3,"name":"Blair","gender":"male"},{"id":4,"name":"Lilah","gender":"famale"},{"id":5,"name":"Bobbette","gender":"male"},{"id":6,"name":"Danny","gender":"famale"},{"id":7,"name":"Charlotta","gender":"male"},{"id":8,"name":"Horatia","gender":"male"},{"id":9,"name":"Pierrette","gender":"famale"},{"id":10,"name":"Xenia","gender":"male"},{"id":11,"name":"Evangeline","gender":"male"},{"id":12,"name":"Andy","gender":"male"},{"id":13,"name":"Regan","gender":"male"},{"id":14,"name":"Tedra","gender":"male"},{"id":15,"name":"Nanine","gender":"male"},{"id":16,"name":"Ailee","gender":"male"},{"id":17,"name":"Erminia","gender":"male"},{"id":18,"name":"Lottie","gender":"male"},{"id":19,"name":"Leta","gender":"famale"},{"id":20,"name":"Coralie","gender":"male"},{"id":21,"name":"Lexie","gender":"male"},{"id":22,"name":"Tasha","gender":"male"},{"id":23,"name":"Lynn","gender":"male"},{"id":24,"name":"Ester","gender":"famale"},{"id":25,"name":"Marthe","gender":"famale"},{"id":26,"name":"Dawna","gender":"famale"},{"id":27,"name":"Austin","gender":"famale"},{"id":28,"name":"Silvia","gender":"famale"},{"id":29,"name":"Happy","gender":"male"},{"id":30,"name":"Catarina","gender":"famale"},{"id":31,"name":"Cicely","gender":"male"},{"id":32,"name":"Fred","gender":"male"},{"id":33,"name":"Cristionna","gender":"famale"},{"id":34,"name":"Arabela","gender":"male"},{"id":35,"name":"Jemie","gender":"famale"},{"id":36,"name":"Sophia","gender":"male"},{"id":37,"name":"Cairistiona","gender":"famale"},{"id":38,"name":"Shelli","gender":"famale"},{"id":39,"name":"Aretha","gender":"male"},{"id":40,"name":"Andromache","gender":"famale"},{"id":41,"name":"Erminia","gender":"male"},{"id":42,"name":"Lucretia","gender":"famale"},{"id":43,"name":"Zarla","gender":"famale"},{"id":44,"name":"Hortense","gender":"famale"},{"id":45,"name":"Lynn","gender":"male"},{"id":46,"name":"Jammie","gender":"famale"},{"id":47,"name":"Eleonore","gender":"male"},{"id":48,"name":"Elisabet","gender":"famale"},{"id":49,"name":"Austine","gender":"famale"},{"id":50,"name":"Marcie","gender":"male"},{"id":51,"name":"Kim","gender":"famale"},{"id":52,"name":"Lissi","gender":"male"},{"id":53,"name":"Sibylla","gender":"famale"},{"id":54,"name":"Shaina","gender":"famale"},{"id":55,"name":"Marni","gender":"male"},{"id":56,"name":"Junette","gender":"male"},{"id":57,"name":"Karen","gender":"famale"},{"id":58,"name":"Dorree","gender":"male"},{"id":59,"name":"Mickie","gender":"famale"},{"id":60,"name":"Harley","gender":"male"},{"id":61,"name":"Ammamaria","gender":"male"},{"id":62,"name":"Tine","gender":"male"},{"id":63,"name":"Emily","gender":"male"},{"id":64,"name":"Dreddy","gender":"famale"},{"id":65,"name":"Marjory","gender":"male"},{"id":66,"name":"Wren","gender":"famale"},{"id":67,"name":"Lenna","gender":"male"},{"id":68,"name":"Juana","gender":"male"},{"id":69,"name":"Adena","gender":"male"},{"id":70,"name":"Gypsy","gender":"famale"},{"id":71,"name":"Ardeen","gender":"male"},{"id":72,"name":"Cathrin","gender":"male"},{"id":73,"name":"Adelind","gender":"male"},{"id":74,"name":"Brittaney","gender":"famale"},{"id":75,"name":"Zsa Zsa","gender":"famale"},{"id":76,"name":"Daisie","gender":"famale"},{"id":77,"name":"Anallise","gender":"famale"},{"id":78,"name":"Birgitta","gender":"famale"},{"id":79,"name":"Gilemette","gender":"male"},{"id":80,"name":"Karilynn","gender":"famale"},{"id":81,"name":"Jaine","gender":"famale"},{"id":82,"name":"Shauna","gender":"famale"},{"id":83,"name":"Christan","gender":"male"},{"id":84,"name":"Melitta","gender":"male"},{"id":85,"name":"Jaimie","gender":"male"},{"id":86,"name":"Angelita","gender":"male"},{"id":87,"name":"Dreddy","gender":"famale"},{"id":88,"name":"Oralee","gender":"famale"},{"id":89,"name":"Yvonne","gender":"famale"},{"id":90,"name":"Mildrid","gender":"famale"},{"id":91,"name":"Ammamaria","gender":"male"},{"id":92,"name":"Seana","gender":"male"},{"id":93,"name":"Petronilla","gender":"famale"},{"id":94,"name":"Veradis","gender":"famale"},{"id":95,"name":"Davida","gender":"male"},{"id":96,"name":"Sandy","gender":"famale"},{"id":97,"name":"Tiffani","gender":"famale"},{"id":98,"name":"Edwina","gender":"male"},{"id":99,"name":"Zora","gender":"male"},{"id":100,"name":"Cecelia","gender":"male"},{"id":101,"name":"Catrina","gender":"famale"},{"id":102,"name":"Sandie","gender":"famale"},{"id":103,"name":"Lanna","gender":"famale"},{"id":104,"name":"Korrie","gender":"male"},{"id":105,"name":"Amandi","gender":"famale"},{"id":106,"name":"Margery","gender":"male"},{"id":107,"name":"Marnia","gender":"famale"},{"id":108,"name":"Beverie","gender":"male"},{"id":109,"name":"Hildegaard","gender":"famale"},{"id":110,"name":"Alla","gender":"famale"},{"id":111,"name":"Florette","gender":"male"},{"id":112,"name":"Kathe","gender":"famale"},{"id":113,"name":"Bobbi","gender":"famale"},{"id":114,"name":"Correy","gender":"male"},{"id":115,"name":"Esme","gender":"male"},{"id":116,"name":"Astrix","gender":"famale"},{"id":117,"name":"Charita","gender":"famale"},{"id":118,"name":"Doralin","gender":"male"},{"id":119,"name":"Dorian","gender":"male"},{"id":120,"name":"Sunshine","gender":"male"},{"id":121,"name":"Venus","gender":"famale"},{"id":122,"name":"Ailyn","gender":"male"},{"id":123,"name":"Elyse","gender":"famale"},{"id":124,"name":"Etheline","gender":"famale"},{"id":125,"name":"Christine","gender":"famale"},{"id":126,"name":"Ariadne","gender":"famale"},{"id":127,"name":"Janeczka","gender":"famale"},{"id":128,"name":"Susannah","gender":"male"},{"id":129,"name":"Ashli","gender":"famale"},{"id":130,"name":"Isabel","gender":"famale"},{"id":131,"name":"Libbi","gender":"male"},{"id":132,"name":"Henryetta","gender":"famale"},{"id":133,"name":"Sybil","gender":"famale"},{"id":134,"name":"Tawsha","gender":"famale"},{"id":135,"name":"Ameline","gender":"male"},{"id":136,"name":"Michele","gender":"famale"},{"id":137,"name":"Joelynn","gender":"famale"},{"id":138,"name":"Cyb","gender":"famale"},{"id":139,"name":"Basia","gender":"male"},{"id":140,"name":"Rubia","gender":"male"},{"id":141,"name":"Delores","gender":"male"},{"id":142,"name":"Karol","gender":"famale"},{"id":143,"name":"Karen","gender":"famale"},{"id":144,"name":"Elissa","gender":"male"},{"id":145,"name":"Rozele","gender":"male"},{"id":146,"name":"Anett","gender":"famale"},{"id":147,"name":"Brunhilde","gender":"famale"},{"id":148,"name":"Marquita","gender":"famale"},{"id":149,"name":"Joceline","gender":"famale"},{"id":150,"name":"Linette","gender":"famale"},{"id":151,"name":"Marena","gender":"male"},{"id":152,"name":"Emalia","gender":"famale"},{"id":153,"name":"Maris","gender":"famale"},{"id":154,"name":"Delilah","gender":"male"},{"id":155,"name":"Lynnell","gender":"male"},{"id":156,"name":"Junina","gender":"famale"},{"id":157,"name":"Shantee","gender":"famale"},{"id":158,"name":"Jayme","gender":"male"},{"id":159,"name":"Katrine","gender":"male"},{"id":160,"name":"Vally","gender":"famale"},{"id":161,"name":"Yevette","gender":"male"},{"id":162,"name":"Adey","gender":"famale"},{"id":163,"name":"Jeanne","gender":"famale"},{"id":164,"name":"Wynnie","gender":"male"},{"id":165,"name":"Joanne","gender":"famale"},{"id":166,"name":"Emeline","gender":"famale"},{"id":167,"name":"Hanna","gender":"male"},{"id":168,"name":"Olivette","gender":"male"},{"id":169,"name":"Kessiah","gender":"male"},{"id":170,"name":"Myrah","gender":"male"},{"id":171,"name":"Tressa","gender":"famale"},{"id":172,"name":"Amity","gender":"famale"},{"id":173,"name":"Britte","gender":"male"},{"id":174,"name":"Irina","gender":"male"},{"id":175,"name":"Cynthea","gender":"male"},{"id":176,"name":"Colline","gender":"famale"},{"id":177,"name":"Karita","gender":"male"},{"id":178,"name":"Maisie","gender":"male"},{"id":179,"name":"Harrietta","gender":"male"},{"id":180,"name":"Yoko","gender":"famale"},{"id":181,"name":"Tildy","gender":"male"},{"id":182,"name":"Blythe","gender":"famale"},{"id":183,"name":"Elvina","gender":"famale"},{"id":184,"name":"Marcy","gender":"famale"},{"id":185,"name":"Avivah","gender":"famale"},{"id":186,"name":"Gerianne","gender":"male"},{"id":187,"name":"Lenee","gender":"famale"},{"id":188,"name":"Becka","gender":"male"},{"id":189,"name":"Naoma","gender":"male"},{"id":190,"name":"Aleda","gender":"famale"},{"id":191,"name":"Madella","gender":"male"},{"id":192,"name":"Amalee","gender":"male"},{"id":193,"name":"Sandy","gender":"famale"},{"id":194,"name":"Idell","gender":"famale"},{"id":195,"name":"Vikki","gender":"male"},{"id":196,"name":"Alvina","gender":"famale"},{"id":197,"name":"Fay","gender":"famale"},{"id":198,"name":"Jonie","gender":"male"},{"id":199,"name":"Kikelia","gender":"famale"},{"id":200,"name":"Jeanine","gender":"famale"},{"id":201,"name":"Jacquette","gender":"famale"},{"id":202,"name":"Rachael","gender":"famale"},{"id":203,"name":"Ronni","gender":"famale"},{"id":204,"name":"Bird","gender":"male"},{"id":205,"name":"Raychel","gender":"male"},{"id":206,"name":"Melva","gender":"famale"},{"id":207,"name":"Babbie","gender":"famale"},{"id":208,"name":"Linette","gender":"famale"},{"id":209,"name":"Bliss","gender":"male"},{"id":210,"name":"Klara","gender":"famale"},{"id":211,"name":"Minta","gender":"famale"},{"id":212,"name":"Rosemarie","gender":"famale"},{"id":213,"name":"Dynah","gender":"famale"},{"id":214,"name":"Glenda","gender":"male"},{"id":215,"name":"Marline","gender":"male"},{"id":216,"name":"Amandie","gender":"male"},{"id":217,"name":"Abra","gender":"famale"},{"id":218,"name":"Mame","gender":"famale"},{"id":219,"name":"Lesly","gender":"famale"},{"id":220,"name":"Rasia","gender":"male"},{"id":221,"name":"Janene","gender":"famale"},{"id":222,"name":"Vonny","gender":"famale"},{"id":223,"name":"Millie","gender":"male"},{"id":224,"name":"Maddalena","gender":"male"},{"id":225,"name":"Annalise","gender":"male"},{"id":226,"name":"Verna","gender":"male"},{"id":227,"name":"Lilas","gender":"male"},{"id":228,"name":"Grissel","gender":"male"},{"id":229,"name":"Tomi","gender":"famale"},{"id":230,"name":"Sharl","gender":"famale"},{"id":231,"name":"Starr","gender":"famale"},{"id":232,"name":"Aurore","gender":"male"},{"id":233,"name":"Rita","gender":"male"},{"id":234,"name":"Tabby","gender":"famale"},{"id":235,"name":"Cassandry","gender":"male"},{"id":236,"name":"Mariann","gender":"male"},{"id":237,"name":"Emelia","gender":"famale"},{"id":238,"name":"Kally","gender":"famale"},{"id":239,"name":"Damita","gender":"famale"},{"id":240,"name":"Leena","gender":"male"},{"id":241,"name":"Appolonia","gender":"famale"},{"id":242,"name":"Stevana","gender":"famale"},{"id":243,"name":"Binny","gender":"famale"},{"id":244,"name":"Imojean","gender":"male"},{"id":245,"name":"Odelinda","gender":"famale"},{"id":246,"name":"Gwyneth","gender":"famale"},{"id":247,"name":"Elbertine","gender":"famale"},{"id":248,"name":"Amara","gender":"male"},{"id":249,"name":"Veda","gender":"famale"},{"id":250,"name":"Chiarra","gender":"famale"},{"id":251,"name":"Alyse","gender":"male"},{"id":252,"name":"Charmaine","gender":"famale"},{"id":253,"name":"Reiko","gender":"famale"},{"id":254,"name":"Bella","gender":"male"},{"id":255,"name":"Ciel","gender":"male"},{"id":256,"name":"Phylys","gender":"famale"},{"id":257,"name":"Charyl","gender":"famale"},{"id":258,"name":"Sydney","gender":"male"},{"id":259,"name":"Sena","gender":"male"},{"id":260,"name":"Bernita","gender":"famale"},{"id":261,"name":"Kipp","gender":"famale"},{"id":262,"name":"Rachael","gender":"famale"},{"id":263,"name":"Rochelle","gender":"famale"},{"id":264,"name":"Buffy","gender":"male"},{"id":265,"name":"Nadia","gender":"famale"},{"id":266,"name":"Sheilah","gender":"famale"},{"id":267,"name":"Jyoti","gender":"famale"},{"id":268,"name":"Marianne","gender":"male"},{"id":269,"name":"Felecia","gender":"famale"},{"id":270,"name":"Jasmin","gender":"famale"},{"id":271,"name":"Yalonda","gender":"famale"},{"id":272,"name":"Sabine","gender":"male"},{"id":273,"name":"Merralee","gender":"male"},{"id":274,"name":"Dierdre","gender":"famale"},{"id":275,"name":"Glennie","gender":"male"},{"id":276,"name":"Enid","gender":"male"},{"id":277,"name":"Tiphanie","gender":"male"},{"id":278,"name":"Joni","gender":"famale"},{"id":279,"name":"Gavra","gender":"male"},{"id":280,"name":"Margarita","gender":"male"},{"id":281,"name":"Leia","gender":"male"},{"id":282,"name":"Annadiane","gender":"famale"},{"id":283,"name":"Shae","gender":"male"},{"id":284,"name":"Ilse","gender":"famale"},{"id":285,"name":"Wenona","gender":"famale"},{"id":286,"name":"Brinna","gender":"male"},{"id":287,"name":"Matilde","gender":"male"},{"id":288,"name":"Liliane","gender":"famale"},{"id":289,"name":"Tanhya","gender":"famale"},{"id":290,"name":"Jacklyn","gender":"male"},{"id":291,"name":"Anjanette","gender":"male"},{"id":292,"name":"Hetti","gender":"famale"},{"id":293,"name":"Freddy","gender":"male"},{"id":294,"name":"Vin","gender":"male"},{"id":295,"name":"Shell","gender":"famale"},{"id":296,"name":"Elbertine","gender":"famale"},{"id":297,"name":"Bill","gender":"male"},{"id":298,"name":"Becca","gender":"famale"},{"id":299,"name":"Raquela","gender":"famale"},{"id":300,"name":"Christyna","gender":"male"},{"id":301,"name":"Inna","gender":"male"},{"id":302,"name":"Athene","gender":"male"},{"id":303,"name":"Henrieta","gender":"male"},{"id":304,"name":"Annmarie","gender":"male"},{"id":305,"name":"Carolan","gender":"male"},{"id":306,"name":"Zsazsa","gender":"male"},{"id":307,"name":"Letizia","gender":"male"},{"id":308,"name":"Sabra","gender":"famale"},{"id":309,"name":"Bessie","gender":"famale"},{"id":310,"name":"Vikky","gender":"famale"},{"id":311,"name":"Edita","gender":"male"},{"id":312,"name":"Sabine","gender":"male"},{"id":313,"name":"Tiffi","gender":"male"},{"id":314,"name":"Edin","gender":"famale"},{"id":315,"name":"Bria","gender":"male"},{"id":316,"name":"Kathie","gender":"male"},{"id":317,"name":"Terrijo","gender":"famale"},{"id":318,"name":"Delora","gender":"famale"},{"id":319,"name":"Engracia","gender":"famale"},{"id":320,"name":"Berta","gender":"famale"},{"id":321,"name":"Jenelle","gender":"famale"},{"id":322,"name":"Storm","gender":"male"},{"id":323,"name":"Ketty","gender":"famale"},{"id":324,"name":"Virginie","gender":"famale"},{"id":325,"name":"Georgine","gender":"famale"},{"id":326,"name":"Kelsey","gender":"male"},{"id":327,"name":"Marleen","gender":"famale"},{"id":328,"name":"Caitrin","gender":"famale"},{"id":329,"name":"Thomasine","gender":"male"},{"id":330,"name":"Rosalind","gender":"male"},{"id":331,"name":"Emmi","gender":"male"},{"id":332,"name":"Malina","gender":"male"},{"id":333,"name":"Mavra","gender":"famale"},{"id":334,"name":"Elsie","gender":"famale"},{"id":335,"name":"Rasla","gender":"famale"},{"id":336,"name":"Mavis","gender":"male"},{"id":337,"name":"Molli","gender":"famale"},{"id":338,"name":"Layney","gender":"famale"},{"id":339,"name":"Jeniffer","gender":"male"},{"id":340,"name":"Elsinore","gender":"male"},{"id":341,"name":"Darleen","gender":"male"},{"id":342,"name":"Chloette","gender":"male"},{"id":343,"name":"Suzette","gender":"famale"},{"id":344,"name":"Zorana","gender":"male"},{"id":345,"name":"Alameda","gender":"male"},{"id":346,"name":"Bobbee","gender":"famale"},{"id":347,"name":"Ursola","gender":"male"},{"id":348,"name":"Ofilia","gender":"famale"},{"id":349,"name":"Alameda","gender":"male"},{"id":350,"name":"Michel","gender":"male"},{"id":351,"name":"Dionne","gender":"famale"},{"id":352,"name":"Liesa","gender":"male"},{"id":353,"name":"Tova","gender":"famale"},{"id":354,"name":"Roobbie","gender":"famale"},{"id":355,"name":"Barbie","gender":"male"},{"id":356,"name":"Eudora","gender":"male"},{"id":357,"name":"Konstance","gender":"male"},{"id":358,"name":"Andrei","gender":"famale"},{"id":359,"name":"Trina","gender":"famale"},{"id":360,"name":"Evy","gender":"male"},{"id":361,"name":"Katina","gender":"male"},{"id":362,"name":"Ivette","gender":"famale"},{"id":363,"name":"Aryn","gender":"male"},{"id":364,"name":"Larisa","gender":"famale"},{"id":365,"name":"Gwen","gender":"male"},{"id":366,"name":"Monah","gender":"male"},{"id":367,"name":"Dorree","gender":"male"},{"id":368,"name":"Marcy","gender":"famale"},{"id":369,"name":"Vannie","gender":"male"},{"id":370,"name":"Morena","gender":"male"},{"id":371,"name":"Nelly","gender":"famale"},{"id":372,"name":"Shaylah","gender":"famale"},{"id":373,"name":"Allison","gender":"male"},{"id":374,"name":"Martita","gender":"famale"},{"id":375,"name":"Dyana","gender":"famale"},{"id":376,"name":"Ladonna","gender":"famale"},{"id":377,"name":"Yvonne","gender":"famale"},{"id":378,"name":"Tamma","gender":"male"},{"id":379,"name":"Joan","gender":"famale"},{"id":380,"name":"Misti","gender":"male"},{"id":381,"name":"Ana","gender":"famale"},{"id":382,"name":"Julita","gender":"male"},{"id":383,"name":"Vinnie","gender":"male"},{"id":384,"name":"Marrissa","gender":"male"},{"id":385,"name":"Nina","gender":"male"},{"id":386,"name":"Rosalind","gender":"male"},{"id":387,"name":"Valaria","gender":"famale"},{"id":388,"name":"Conni","gender":"famale"},{"id":389,"name":"Effie","gender":"male"},{"id":390,"name":"Gabie","gender":"male"},{"id":391,"name":"Callida","gender":"famale"},{"id":392,"name":"Friederike","gender":"famale"},{"id":393,"name":"Lane","gender":"famale"},{"id":394,"name":"Janine","gender":"famale"},{"id":395,"name":"Rowena","gender":"male"},{"id":396,"name":"Feliza","gender":"male"},{"id":397,"name":"Adelle","gender":"famale"},{"id":398,"name":"Terrye","gender":"famale"},{"id":399,"name":"Elie","gender":"famale"},{"id":400,"name":"Caresse","gender":"male"},{"id":401,"name":"Samantha","gender":"famale"},{"id":402,"name":"Livvy","gender":"famale"},{"id":403,"name":"Arabela","gender":"male"},{"id":404,"name":"Letta","gender":"famale"},{"id":405,"name":"Mechelle","gender":"famale"},{"id":406,"name":"Ashleigh","gender":"male"},{"id":407,"name":"Flore","gender":"male"},{"id":408,"name":"Elizabet","gender":"famale"},{"id":409,"name":"Krystalle","gender":"male"},{"id":410,"name":"Larina","gender":"famale"},{"id":411,"name":"Lenora","gender":"famale"},{"id":412,"name":"Antonella","gender":"male"},{"id":413,"name":"Terry","gender":"male"},{"id":414,"name":"Regan","gender":"male"},{"id":415,"name":"Xylina","gender":"male"},{"id":416,"name":"Susanetta","gender":"famale"},{"id":417,"name":"Chickie","gender":"male"},{"id":418,"name":"Jamima","gender":"male"},{"id":419,"name":"Allegra","gender":"famale"},{"id":420,"name":"Devinne","gender":"male"},{"id":421,"name":"Annabella","gender":"male"},{"id":422,"name":"Lilyan","gender":"famale"},{"id":423,"name":"Franny","gender":"male"},{"id":424,"name":"Astra","gender":"famale"},{"id":425,"name":"Gloriane","gender":"famale"},{"id":426,"name":"Mavra","gender":"famale"},{"id":427,"name":"Blair","gender":"male"},{"id":428,"name":"Binnie","gender":"male"},{"id":429,"name":"Daffi","gender":"famale"}]